polygon_geohasher/__init__.py
polygon_geohasher/polygon_geohasher.py
polygon_geohasher/py.typed
polygon_geohasher/version.py
polygon_geohasher_2-0.2.0.dist-info/licenses/LICENSE
tests/__init__.py
tests/main_test.py
polygon_geohasher_2-0.2.0.dist-info/METADATA
polygon_geohasher_2-0.2.0.dist-info/WHEEL
polygon_geohasher_2-0.2.0.dist-info/top_level.txt
polygon_geohasher_2-0.2.0.dist-info/RECORD
