Metadata-Version: 2.4
Name: polygon-geohasher-2
Version: 0.2.0
Summary: Wrapper over Shapely that returns the set of geohashes that form a Polygon.
Home-page: https://github.com/duckontheweb/polygon-geohasher
Author: Alberto Bonsanto; maintained by Jon Duckworth
Author-email: 
License: MIT
Keywords: polygon,geohashes
Classifier: Development Status :: 3 - Alpha
Classifier: Intended Audience :: Developers
Classifier: Topic :: Software Development :: Libraries :: Python Modules
Classifier: License :: OSI Approved :: MIT License
Classifier: Programming Language :: Python :: 3.10
Classifier: Programming Language :: Python :: 3.11
Classifier: Programming Language :: Python :: 3.12
Classifier: Programming Language :: Python :: 3.13
Classifier: Programming Language :: Python :: 3.14
Requires-Python: >=3.10,<3.15
License-File: LICENSE
Requires-Dist: shapely~=2.0; python_version >= "3.12"
Requires-Dist: shapely<3,>=1; python_version < "3.12"
Requires-Dist: python-geohash>=0.8.5
Dynamic: author
Dynamic: classifier
Dynamic: description
Dynamic: description-content-type
Dynamic: home-page
Dynamic: keywords
Dynamic: license
Dynamic: license-file
Dynamic: requires-dist
Dynamic: requires-python
Dynamic: summary
